pysampled/__init__.py
pysampled/__version__.py
pysampled/core.py
pysampled/download_airpls.py
pysampled-1.1.1.dist-info/entry_points.txt
pysampled-1.1.1.dist-info/LICENSE
pysampled-1.1.1.dist-info/WHEEL
pysampled-1.1.1.dist-info/METADATA
pysampled-1.1.1.dist-info/RECORD
