Metadata-Version: 2.1
Name: pysampled
Version: 1.1.1
Summary: A toolkit for working with uniformly sampled time series data.
Author-email: Praneeth Namburi <praneeth.namburi@gmail.com>
Requires-Python: >=3.7
Classifier: Development Status :: 5 - Production/Stable
Classifier: License :: OSI Approved :: MIT License
Classifier: Topic :: Scientific/Engineering
Classifier: Programming Language :: Python
Classifier: Programming Language :: Python :: 3.7
Classifier: Programming Language :: Python :: 3.8
Classifier: Programming Language :: Python :: 3.9
Classifier: Programming Language :: Python :: 3.10
Classifier: Programming Language :: Python :: 3.11
Classifier: Programming Language :: Python :: 3.12
Classifier: Programming Language :: Python :: Implementation :: CPython
Classifier: Programming Language :: Python :: Implementation :: PyPy
Requires-Dist: numpy
Requires-Dist: scipy
Requires-Dist: scikit-learn
Requires-Dist: matplotlib
Requires-Dist: numpy ; extra == "minimal"
Requires-Dist: scipy ; extra == "minimal"
Project-URL: Home, https://github.com/praneethnamburi/pysampled
Provides-Extra: minimal
